{"212367433":{"brand":"Bladex","model":"BX30-24HPHYHA"},"205663358":{"brand":"DAIKIN","model":"3MXL24RMVJU*"},"205047852":{"brand":"PANASONIC","model":"CU-XE12WKUA"},"207256441":{"brand":"GREE","model":"FLEXX36HP230V1AO"},"8033586":{"brand":"FUJITSU","model":"AOU24RLXFZH"},"207706559":{"brand":"MOOVAIR","model":"DMA24HOS20230E7"},"207599994":{"brand":"DAIKIN","model":"DZ17VSA301B*"},"206249116":{"brand":"GREE","model":"GUD36W/A-D(U)"},"210722665":{"brand":"DAIKIN","model":"3MXL24WMVJU*"},"205123809":{"brand":"FUJITSU","model":"AOUG36LMAS1"},"206249117":{"brand":"GREE","model":"GUD36W/A-D(U)"},"204717600":{"brand":"DAIKIN","model":"RXL12QMVJU9"},"205663349":{"brand":"DAIKIN","model":"RXL15QMVJU*"},"204825178":{"brand":"LG","model":"LAU120HYV3"},"7091971":{"brand":"GREE","model":"GWH12QC-D3DNA1D/O"},"206597213":{"brand":"FUJITSU","model":"AOUG15LZAH1"},"201851577":{"brand":"DAIKIN","model":"3MXL24RMVJU"},"205047853":{"brand":"PANASONIC","model":"CU-XE15WKUA"},"8703508":{"brand":"FUJITSU","model":"AOU15RLS3H"},"207768730":{"brand":"LENNOX","model":"MLB030S4M-1P"},"201863352":{"brand":"ACD","model":"OCD18KCH20S-O"},"211644151":{"brand":"GREE","model":"GUD36W/A-D(U)"},"212361760":{"brand":"MOOVAIR","model":"DMA30HOS20230E7"},"205663354":{"brand":"DAIKIN","model":"2MXL18QMVJU*"},"206414274":{"brand":"TOSOT","model":"TU60-48WADU"},"207657396":{"brand":"KERR","model":"A-KMH18SV-1"},"207202288":{"brand":"CARRIER","model":"38MARBQ18AA3"},"212361758":{"brand":"MOOVAIR","model":"DMA18HOS20230E7"},"213153602":{"brand":"NAPOLEON","model":"WSEHV2436RA1-N"},"206903532":{"brand":"HISENSE","model":"AUWR-24U3SF2"},"203025011":{"brand":"BOSCH","model":"BOVA-36HDN1-M20G"},"212361362":{"brand":"KINGHOME","model":"KU36UHO"},"207098550":{"brand":"CARRIER","model":"38MARBQ24AA3"},"10570123":{"brand":"LG","model":"LSU120HSV5"},"212361759":{"brand":"MOOVAIR","model":"DMA24HOS20230E7"},"206414273":{"brand":"TOSOT","model":"TU36-24WADU"},"212361366":{"brand":"TOSOT","model":"TU36-24WADU"}}